{
    "countries": {
      "Bahrain": "https://i.postimg.cc/tCfG6kqV/bahrain.jpg",
      "Saudi Arabia": "https://i.postimg.cc/02rqrFss/saudi-arabia.jpg",
      "Australia": "https://i.postimg.cc/qv3VxKqD/australia.jpg",
      "Japan": "https://i.postimg.cc/9fH38fqm/japan.jpg",
      "China": "https://i.postimg.cc/436DrTzz/china.jpg",
      "Monaco": "https://i.postimg.cc/hjMHtbZv/monaco.jpg",
      "Canada": "https://i.postimg.cc/XqJtGGt8/canada.jpg",
      "Spain": "https://i.postimg.cc/KjHwnc2y/spain.jpg",
      "Austria": "https://i.postimg.cc/XNHRMLyD/austria.jpg",
      "UK": "https://i.postimg.cc/7ZS9pTPW/uk.jpg",
      "Hungary": "https://i.postimg.cc/bNZKqnxY/hungary.jpg",
      "Belgium": "https://i.postimg.cc/FswwzKpy/belgium.jpg",
      "Netherlands": "https://i.postimg.cc/y89tZzpw/netherlands.jpg",
      "Italy": "https://i.postimg.cc/7PFpY6mg/italy.jpg",
      "Azerbaijan": "https://i.postimg.cc/1zQT0YL4/azerbaijan.jpg",
      "Singapore": "https://i.postimg.cc/Ls3Wx3pD/singapore.jpg",
      "USA": "https://i.postimg.cc/xC9wQFRB/united-states-of-america.jpg",
      "Mexico": "https://i.postimg.cc/RFCDyJCB/mexico.jpg",
      "Brazil": "https://i.postimg.cc/xCs42jqb/brazil.jpg",
      "Qatar": "https://i.postimg.cc/D08YyVbp/qatar.jpg",
      "Abu Dhabi": "https://i.postimg.cc/x8hpXsvf/united-arab-emirates.jpg",
      "Portugal": "https://i.postimg.cc/hty9BQP1/portugal.jpg",
      "Argentina": "https://i.postimg.cc/yx4mGqYq/argentina.jpg",
      "France": "https://i.postimg.cc/MH772svn/france.jpg",
      "Germany": "https://i.postimg.cc/05DdwNc9/germany.jpg",
      "Kazakhstan": "https://i.postimg.cc/cJvf41vy/kazakhstan.jpg",
      "San Marino": "https://i.postimg.cc/hGNTJFmJ/san-marino.jpg",
      "India": "https://i.postimg.cc/fTvc8gGF/india.jpg",
      "Indonesia": "https://i.postimg.cc/xTQGyS4M/indonesia.jpg",
      "Thailand": "https://i.postimg.cc/Qt5516gf/thailand.jpg",
      "Malaysia": "https://i.postimg.cc/bwNQW98v/malaysia.jpg"
    },
    "calendar": {
      "01": "Australia",
      "02": "China",
      "03": "Japan",
      "04": "Bahrain",
      "05": "Saudi Arabia",
      "06": "USA",
      "07": "Italy",
      "08": "Monaco",
      "09": "Spain",
      "10": "Canada",
      "11": "Austria",
      "12": "UK",
      "13": "Belgium",
      "14": "Hungary",
      "15": "Netherlands",
      "16": "Italy",
      "17": "Azerbaijan",
      "18": "Singapore",
      "19": "USA",
      "20": "Mexico",
      "21": "Brazil",
      "22": "USA",
      "23": "Qatar",
      "24": "Abu Dhabi"
    }
  }

